{
   "Leaders": [
      {
         "data": "George Washington"
      },
      {
         "data": "Abraham Lincoln"
      },
      {
         "data": "Thomas Jefferson"
      },
      {
         "data": "Alexander The Great"
      },
      {
         "data": "Martin Luther King Jr."
      },
      {
         "data": "James Madison"
      },
      {
         "data": "Donald Trump"
      },
      {
         "data": "Napoleon Bonaparte"
      },
      {
         "data": "Charlemagne"
      },
      {
         "data": "Augustus Caesar"
      },
      {
         "data": "Thomas Paine"
      },
      {
         "data": "Julius Caesar"
      },
      {
         "data": "John F. Kennedy"
      },
      {
         "data": "Otto von Bismarck"
      },
      {
         "data": "John Locke"
      },
      {
         "data": "Elizabeth I of England"
      },
      {
         "data": "Mahatma Gandhi"
      },
      {
         "data": "Benjamin Franklin"
      },
      {
         "data": "Joan of Arc"
      },
      {
         "data": "Nelson Mandela"
      },
      {
         "data": "William the Conqueror"
      },
      {
         "data": "Peter the Great"
      },
      {
         "data": "Constantine the Great"
      },
      {
         "data": "Mustafa Kemal Atatürk"
      },
      {
         "data": "Mother Teresa"
      },
      {
         "data": "Moses"
      },
      {
         "data": "Winston Churchill"
      },
      {
         "data": "Catherine the Great"
      },
      {
         "data": "Otto I the Great, Holy Roman Emperor"
      },
      {
         "data": "James Monroe"
      },
      {
         "data": "Arminius"
      },
      {
         "data": "Leif Ericson"
      },
      {
         "data": "Alfred the Great"
      },
      {
         "data": "Richard I. of England"
      },
      {
         "data": "Patrick Henry"
      },
      {
         "data": "Leonidas I"
      },
      {
         "data": "John Hancock"
      },
      {
         "data": "Jesus Christ"
      },
      {
         "data": "Robert F. Kennedy"
      },
      {
         "data": "Attila the Hun"
      },
      {
         "data": "Nebuchadnezzar II"
      },
      {
         "data": "Sultan Mehmed II"
      },
      {
         "data": "Joseph Stalin"
      },
      {
         "data": "Martin Luther"
      },
      {
         "data": "Salah al-Din"
      },
      {
         "data": "Suleyman The Magnificent"
      },
      {
         "data": "William I., German Emperor"
      },
      {
         "data": "Hannibal Barca"
      },
      {
         "data": "Gustavus Adolphus of Sweden"
      },
      {
         "data": "Pericles"
      },
      {
         "data": "Cleopatra"
      },
      {
         "data": "Marcus Aurelius"
      },
      {
         "data": "Hammurabi"
      },
      {
         "data": "Queen Victoria"
      },
      {
         "data": "Sun Tzu"
      },
      {
         "data": "Ronald Reagan"
      },
      {
         "data": "Titus"
      },
      {
         "data": "Vladimir Putin"
      },
      {
         "data": "Eric the Red"
      },
      {
         "data": "Franklin D. Roosevelt"
      },
      {
         "data": "Theoderic the Great"
      },
      {
         "data": "Robert E. Lee"
      },
      {
         "data": "Charles Martel"
      },
      {
         "data": "Adolf Hitler"
      },
      {
         "data": "Hazrat Muhammad"
      },
      {
         "data": "Dmitry Donskoy"
      },
      {
         "data": "Gengis Khan"
      },
      {
         "data": "Maria Theresa"
      },
      {
         "data": "Mao Zedong"
      },
      {
         "data": "Margaret Thatcher"
      },
      {
         "data": "Oliver Cromwell"
      },
      {
         "data": "Selim I"
      },
      {
         "data": "Vladimir Lenin"
      },
      {
         "data": "John Adams"
      },
      {
         "data": "UMAR IBN AL KHATTAB"
      },
      {
         "data": "Charles V, Holy Roman Emperor"
      },
      {
         "data": "Maximilian I, Holy Roman Emperor"
      },
      {
         "data": "Ramses II"
      },
      {
         "data": "Philip II of Macedon"
      },
      {
         "data": "Frederick Barbarossa"
      },
      {
         "data": "John Locke"
      },
      {
         "data": "Erwin Rommel"
      },
      {
         "data": "Scipio Africanus"
      },
      {
         "data": "Quaid-e-Azam Muhammad Ali Jinnah"
      },
      {
         "data": "Rurik"
      },
      {
         "data": "Cnut the Great"
      },
      {
         "data": "T. E. Lawrence of Arabia"
      },
      {
         "data": "Augustus II the Strong"
      },
      {
         "data": "Cardinal Richelieu"
      },
      {
         "data": "Ted Kennedy"
      },
      {
         "data": "Prophet Muhammad"
      },
      {
         "data": "Ho Chi Minh"
      },
      {
         "data": "Christopher Colombus"
      },
      {
         "data": "Widukind"
      },
      {
         "data": "Confucius"
      },
      {
         "data": "Gustav Vasa"
      },
      {
         "data": "Niccolò Machiavelli"
      },
      {
         "data": "William of Orange"
      },
      {
         "data": "Frederick William I of Prussia"
      },
      {
         "data": "Boudicca"
      },
      {
         "data": "Crazy Horse"
      },
      {
         "data": "Gautama Buddha"
      },
      {
         "data": "Helmuth von Moltke the Elder"
      },
      {
         "data": "Mikhail Gorbachev"
      },
      {
         "data": "Kubla Khan"
      },
      {
         "data": "Baldwin I. of Jerusalem"
      },
      {
         "data": "Allama Muhammad Iqbal"
      },
      {
         "data": "Ashoka the Great"
      },
      {
         "data": "Cicero"
      },
      {
         "data": "Elizabeth II"
      },
      {
         "data": "Carl Gustaf Emil Mannerheim"
      },
      {
         "data": "Nikola Jurišić"
      },
      {
         "data": "Franklin Delano Roosevelt, Jr."
      },
      {
         "data": "Gebhard Leberecht Von Blücher"
      },
      {
         "data": "Mark Antony"
      },
      {
         "data": "Sargon the Great"
      },
      {
         "data": "Otto Von Kotzebue"
      },
      {
         "data": "Samuel Adams"
      },
      {
         "data": "Gerold, Prefect of Bavaria"
      },
      {
         "data": "Plato"
      },
      {
         "data": "Albert Einstein"
      },
      {
         "data": "Imran Khan"
      },
      {
         "data": "Vercingetorix"
      },
      {
         "data": "Malcolm X"
      },
      {
         "data": "Charles XII of Sweden"
      },
      {
         "data": "Justinian I"
      },
      {
         "data": "Flavius Odoacer"
      },
      {
         "data": "Karl Marx"
      },
      {
         "data": "Flavius Aetius"
      },
      {
         "data": "Harry S. Truman"
      },
      {
         "data": "Darius The Great"
      },
      {
         "data": "Theodore Roosevelt"
      },
      {
         "data": "Queen Isabella of Spain"
      },
      {
         "data": "Henry VII, Holy Roman Emperor"
      },
      {
         "data": "Isabella I of Castile"
      },
      {
         "data": "Theodoric I"
      },
      {
         "data": "Geronimo"
      },
      {
         "data": "Fidel Castro"
      },
      {
         "data": "Subhash Chandra Bose"
      },
      {
         "data": "Alaric I."
      },
      {
         "data": "Indira Gandhi"
      },
      {
         "data": "Ulrich Von Hutten"
      },
      {
         "data": "Marcus Vipsanius Agrippa"
      },
      {
         "data": "Ivan IV. Grozny the Terrible"
      },
      {
         "data": "Xerxes the Great"
      },
      {
         "data": "Che Guevara"
      },
      {
         "data": "Peter Stuyvesant"
      },
      {
         "data": "Frederick I. Barbarossa, Holy Roman Emperor"
      },
      {
         "data": "King Solomon"
      },
      {
         "data": "Axel Oxenstierna"
      },
      {
         "data": "Lucius Aemilius Paullus Macedonicus"
      },
      {
         "data": "King David"
      },
      {
         "data": "Pepin the Short"
      },
      {
         "data": "Friedrich Wilhelm von Steuben"
      },
      {
         "data": "Ragnar Lodbrok"
      },
      {
         "data": "Woodrow Wilson"
      },
      {
         "data": "Shaka Zulu"
      },
      {
         "data": "Pope John Paul II"
      },
      {
         "data": "Otto I., Holy Roman Emperor"
      },
      {
         "data": "Benito Mussolini"
      },
      {
         "data": "Henry VIII of England"
      },
      {
         "data": "Tamerlane"
      },
      {
         "data": "Adam Smith"
      },
      {
         "data": "Charles Lindbergh"
      },
      {
         "data": "Dwight D. Eisenhower"
      },
      {
         "data": "Lennart Torstensson"
      },
      {
         "data": "Louis XIV of France"
      },
      {
         "data": "Francisco Pizarro"
      },
      {
         "data": "Erich Ludendorff"
      },
      {
         "data": "Charles de Gaulle"
      },
      {
         "data": "Sultan II. Abdulhamid Khan"
      },
      {
         "data": "Simon Bolivar Buckner"
      },
      {
         "data": "Vespasian"
      },
      {
         "data": "Lindbergh"
      },
      {
         "data": "Philip II of Spain"
      },
      {
         "data": "Tecumseh"
      },
      {
         "data": "Hernán Cortés"
      },
      {
         "data": "Edward I of England"
      },
      {
         "data": "Frederick William I. of Prussia"
      },
      {
         "data": "Barack Obama"
      },
      {
         "data": "Emperor Meiji"
      },
      {
         "data": "Vlad III. Drăculea the Impaler"
      },
      {
         "data": "Kaiser Wilhelm II"
      },
      {
         "data": "Tervel of Bulgaria"
      },
      {
         "data": "Maximilien de Robespierre"
      },
      {
         "data": "August Neidhardt Von Gneisenau"
      },
      {
         "data": "Henri de la Rochejaquelein"
      },
      {
         "data": "Toyotomi Hideyoshi"
      },
      {
         "data": "Josip Broz Tito"
      },
      {
         "data": "Miltiades the Younger"
      },
      {
         "data": "Frederick I Barbarossa, Holy Roman Emperor"
      },
      {
         "data": "Pontiac"
      },
      {
         "data": "Gaius Marius"
      },
      {
         "data": "Felix Von Luckner"
      },
      {
         "data": "Henry Vi, Holy Roman Emperor"
      },
      {
         "data": "William Pitt the Younger"
      },
      {
         "data": "Prince Eugene of Savoy"
      },
      {
         "data": "Skanderbeg"
      },
      {
         "data": "Wilhelm II"
      },
      {
         "data": "Haile Selassie"
      },
      {
         "data": "Demosthenes"
      },
      {
         "data": "Leif Ericson"
      },
      {
         "data": "Muhammad Ali Jinnah"
      },
      {
         "data": "Themistocles"
      },
      {
         "data": "John Iii Sobieski"
      },
      {
         "data": "Nikita Khrushchev"
      },
      {
         "data": "Albrecht Von Wallenstein"
      },
      {
         "data": "Frederick I. of Prussia"
      },
      {
         "data": "Aung San Suu Kyi"
      },
      {
         "data": "Mathias Corvinus King of Hungary"
      },
      {
         "data": "Socrates"
      },
      {
         "data": "Aristotle"
      },
      {
         "data": "Anwar Sadat"
      },
      {
         "data": "Leon Trotsky"
      },
      {
         "data": "John Quincy Adams"
      },
      {
         "data": "Rudolf Hess"
      },
      {
         "data": "Ulysses S. Grant"
      },
      {
         "data": "Charles V., Holy Roman Emperor"
      },
      {
         "data": "Timur Lenk of Seljuks"
      },
      {
         "data": "William the Silent"
      },
      {
         "data": "William Pitt, 1st Earl of Chatham"
      },
      {
         "data": "Stonewall Jackson"
      },
      {
         "data": "George W. Bush"
      },
      {
         "data": "Richard Nixon"
      },
      {
         "data": "Alexander Suvorov"
      },
      {
         "data": "Abraham (patriarch)"
      },
      {
         "data": "George III of the United Kingdom"
      },
      {
         "data": "Hideki Tōjō"
      },
      {
         "data": "Golda Meir"
      },
      {
         "data": "Moctezuma I"
      },
      {
         "data": "Cyrus the Great"
      },
      {
         "data": "Frederick II, Holy Roman Emperor"
      },
      {
         "data": "Deng Xiaoping"
      },
      {
         "data": "Alulim"
      },
      {
         "data": "Andrew Jackson"
      },
      {
         "data": "William Tell"
      },
      {
         "data": "Alexander Hamilton"
      },
      {
         "data": "Karl August von Hardenberg"
      },
      {
         "data": "Eva Perón"
      },
      {
         "data": "Frederick William, the Great Elector"
      },
      {
         "data": "Nicholas II of Russia"
      },
      {
         "data": "Yeshua"
      },
      {
         "data": "Claudius"
      },
      {
         "data": "Qin Shi Huang"
      },
      {
         "data": "Arthur Pendragon"
      },
      {
         "data": "King Henry V111"
      },
      {
         "data": "Hernando Cortés"
      },
      {
         "data": "Simón Bolívar Great military and political leader who has liberated many countries in South-America"
      },
      {
         "data": "Angela Merkel"
      },
      {
         "data": "King Hussein of Jordan: A Political Life"
      },
      {
         "data": "Jefferson Davis"
      },
      {
         "data": "Gaspard II de Coligny"
      },
      {
         "data": "Arthur Wellesley, 1st Duke of Wellington"
      },
      {
         "data": "Sheikh Mujibur Rahman"
      },
      {
         "data": "Muammar al-Gaddafi"
      },
      {
         "data": "Helmut Kohl"
      },
      {
         "data": "Horatio Nelson, 1st Viscount Nelson"
      },
      {
         "data": "Lech Wałęsa"
      },
      {
         "data": "Vlad the Impaler"
      },
      {
         "data": "Hermann Göring"
      },
      {
         "data": "Sheikh Zayed"
      },
      {
         "data": "Kublai Khan"
      },
      {
         "data": "Boris Yeltsin"
      },
      {
         "data": "Éamon de Valera"
      },
      {
         "data": "Oda Nobunaga"
      },
      {
         "data": "Bill Clinton"
      },
      {
         "data": "Pope Gregory I"
      },
      {
         "data": "Arthur Zimmermann"
      },
      {
         "data": "David Lloyd George"
      },
      {
         "data": "Khan Abdul Ghaffar Khan"
      },
      {
         "data": "Mahmud of Ghazni"
      },
      {
         "data": "Narendra Modi"
      },
      {
         "data": "Sun Yat-sen"
      },
      {
         "data": "John, King of England"
      },
      {
         "data": "Dr. B. R. Ambedkar"
      },
      {
         "data": "Chiang Kai-shek"
      },
      {
         "data": "Hugo Chávez"
      },
      {
         "data": "Robert the Bruce"
      },
      {
         "data": "Mohammad Mosaddegh"
      },
      {
         "data": "Toussaint Louverture"
      },
      {
         "data": "Zulfikar Ali Bhutto"
      },
      {
         "data": "Galileo Galilei"
      },
      {
         "data": "Robert Ross"
      },
      {
         "data": "Andreas Hofer"
      },
      {
         "data": "Okomfo Anokye"
      },
      {
         "data": "Emiliano Zapata"
      },
      {
         "data": "Chhatrapati Shivaji Maharaj"
      },
      {
         "data": "Lee Kuan Yew"
      },
      {
         "data": "Augusto Pinochet"
      },
      {
         "data": "Ptolemy I Soter"
      },
      {
         "data": "Tupac Yupanqui"
      },
      {
         "data": "Empress Jingū"
      },
      {
         "data": "Ahmad Shah Masoud National Hero"
      },
      {
         "data": "Ahmad Shah Durrani"
      },
      {
         "data": "Agostinho Neto"
      },
      {
         "data": "Leonid Brezhnev"
      },
      {
         "data": "Genghis Khan"
      },
      {
         "data": "John Wilkes"
      },
      {
         "data": "Khan Krum"
      },
      {
         "data": "Heydar Aliyev"
      },
      {
         "data": "Ludwig van Beethoven"
      },
      {
         "data": "King Ine"
      },
      {
         "data": "Moses"
      },
      {
         "data": "Basil I"
      },
      {
         "data": "Francis Bacon"
      },
      {
         "data": "Buddha"
      },
      {
         "data": "Nikephoros II Phokas"
      },
      {
         "data": "Emperor Wu of Han"
      },
      {
         "data": "Emperor Taizong of Tang"
      },
      {
         "data": "Ruhollah Khomeini"
      },
      {
         "data": "Ahmose I"
      },
      {
         "data": "Diocletian"
      },
      {
         "data": "Hatshepsut"
      },
      {
         "data": "Akhenaten"
      },
      {
         "data": "Bashar al-Assad"
      },
      {
         "data": "Francisco Pizarro"
      },
      {
         "data": "Mentuhotep II"
      },
      {
         "data": "Sulla"
      },
      {
         "data": "Kublai Khan"
      },
      {
         "data": "Nezahualcoytl"
      },
      {
         "data": "Timur"
      },
      {
         "data": "Henry the Navigator"
      },
      {
         "data": "Sargon of Akkad"
      },
      {
         "data": "Yongle Emperor"
      },
      {
         "data": "Henry Clay"
      },
      {
         "data": "Mago I"
      },
      {
         "data": "Captain James Cook"
      },
      {
         "data": "Dido I"
      },
      {
         "data": "Simon Bolivar"
      },
      {
         "data": "Empress Dowager Cixi"
      },
      {
         "data": "Ron Paul"
      },
      {
         "data": "Martin McGuinness"
      },
      {
         "data": "Scott Cawthon"
      },
      {
         "data": "James Connolly"
      },
      {
         "data": "Bobby Sands"
      },
      {
         "data": "Patrick Pearse"
      },
      {
         "data": "Brendon Urie"
      },
      {
         "data": "Gerry Adams"
      },
      {
         "data": "Timur Shah Durrani"
      },
      {
         "data": "Paul the Apostle"
      },
      {
         "data": "Pompey"
      },
      {
         "data": "Frederick II of Prussia"
      },
      {
         "data": "Carl von Clausewitz"
      },
      {
         "data": "St. Patrick: Apostle of Ireland"
      },
      {
         "data": "Napoleon III"
      },
      {
         "data": "Muhammad Tahir-ul-Qadri"
      },
      {
         "data": "Vercingetorix"
      },
      {
         "data": "Roald Amundsen"
      },
      {
         "data": "Alexander II of Russia"
      },
      {
         "data": "Frederick II, Holy Roman Emperor"
      },
      {
         "data": "Menes"
      },
      {
         "data": "Abd-ar-Rahman III"
      },
      {
         "data": "William Wallace"
      },
      {
         "data": "Kamehameha I"
      },
      {
         "data": "Charles Maurice de Talleyrand-Périgord"
      },
      {
         "data": "Lao Tsu"
      },
      {
         "data": "Mithradates I of Parthia"
      },
      {
         "data": "Mithridates I of Parthia"
      },
      {
         "data": "Tokugawa Ieyasu"
      },
      {
         "data": "Tony Blair"
      },
      {
         "data": "Pope Urban II"
      },
      {
         "data": "Charles Augustus, Grand Duke of Saxe-Weimar-Eisenach"
      },
      {
         "data": "Emperor Jimmu"
      },
      {
         "data": "Sir Thomas More"
      },
      {
         "data": "Egbert"
      },
      {
         "data": "Erasmus"
      },
      {
         "data": "Mian Nawaz Sharif"
      },
      {
         "data": "Hu the Great"
      },
      {
         "data": "Shinzo Abe"
      },
      {
         "data": "Ivan Iii Vasilyevich"
      },
      {
         "data": "Seleucus I Nicator"
      },
      {
         "data": "Hengist"
      },
      {
         "data": "Alice Paul"
      },
      {
         "data": "José Mujica"
      },
      {
         "data": "Michelle Bachelet"
      },
      {
         "data": "Junichiro Koizumi"
      },
      {
         "data": "Fernando Henrique Cardoso"
      },
      {
         "data": "Maithripala Sirisena"
      },
      {
         "data": "Nasser Mohammad Alyamani."
      },
      {
         "data": "Kevin Smith"
      }
   ]
}
